02_sequential_basics/02_10_serial_to_parallel/02_10_serial_to_parallel.sv
//----------------------------------------------------------------------------
// Task
//----------------------------------------------------------------------------

module serial_to_parallel
# (
    parameter width = 8
)
(
    input                      clk,
    input                      rst,

    input                      serial_valid,
    input                      serial_data,

    output logic               parallel_valid,
    output logic [width - 1:0] parallel_data
);
            
    logic [2:0] count = '0;
    logic [width - 1:0] mem = '0;

    always_comb begin
        if (serial_valid)
            mem[count] = serial_data;
        if (serial_valid & count == (width-1)) begin
            parallel_valid = 1;
            parallel_data = mem;
        end
    end
    
    always_ff @(posedge clk) begin
        if (rst) begin
            count <= '0;
            mem <= '0;
        end
        else begin
            if (serial_valid & count == (width-1)) begin
                parallel_valid <= 0;
                parallel_data <= '0;
                count <= '0;
                mem <= '0;
            end
            else 
                if (serial_valid) begin
                count <= count + 1;
            end
        end
    end
endmodule

02_sequential_basics/02_10_serial_to_parallel/testbench.sv
`include "../include/util.svh"

module testbench;

    // Clock and reset

    logic clk;

    initial
    begin
        clk = '0;

        forever
            # 500 clk = ~ clk;
    end

    logic rst;

    initial
    begin
        rst <= 'x;
        repeat (2) @ (posedge clk);
        rst <= '1;
        repeat (2) @ (posedge clk);
        rst <= '0;
    end

    //------------------------------------------------------------------------

    // Instantiation

    localparam width     = 8;

    localparam n_outputs = 100;
    localparam n_inputs  = n_outputs * width;

    // Minimum to count at least 1000 valid inputs
    localparam in_cnt_w  = $clog2(n_inputs + 1);
    // 8 times smaller than input
    localparam out_cnt_w = $clog2(n_outputs + 1);

    logic                   serial_valid;
    logic                   serial_data;

    wire                    parallel_valid;
    wire  [    width - 1:0] parallel_data;

    logic [ in_cnt_w - 1:0] in_vld_cnt;
    logic [out_cnt_w - 1:0] out_vld_cnt;

    serial_to_parallel  # (.width (width)) dut (.*);

    //------------------------------------------------------------------------

    // Monitor

    bit was_reset = 1'b0;

    logic queue [$];
    logic [width - 1:0] parallel_data_expected;

    always @ (posedge clk)
    begin
        if (rst)
        begin
            was_reset   <= 1'b1;
            out_vld_cnt <= '0;
            in_vld_cnt  <= '0;
            queue        = {};
        end
        else if (was_reset)
        begin
            if (serial_valid) begin
                in_vld_cnt <= in_vld_cnt + 1'b1;

                queue.push_back (serial_data);
            end

            if (parallel_valid)
            begin
                out_vld_cnt <= out_vld_cnt + 1'b1;

                if (queue.size () < width)
                begin
                    $display ("FAIL %s", `__FILE__);

                    $display ("++ TEST     => {%s, %s}",
                        `PD (queue.size ()), `PD (width));

                    $finish (1);
                end
                else
                begin
                    for (int i = 0; i < width; i ++)
                        parallel_data_expected [i] = queue.pop_front ();

                    if (parallel_data !== parallel_data_expected)
                    begin
                        $display ("FAIL %s", `__FILE__);

                        $display ("++ TEST     => {%s, %s}",
                            `PH (parallel_data), `PH (parallel_data_expected));

                        $finish (1);
                    end
                end
            end
        end
    end

    //------------------------------------------------------------------------

    // Stimulus generation

    int current_inputs;
    logic d_serial_valid, d_serial_data;

    initial
    begin
        `ifdef __ICARUS__
            // Uncomment the following line
            // to generate a VCD file and analyze it using GTKwave or Surfer

            $dumpvars;
        `endif

        { serial_valid, serial_data } <= '0;

        @ (negedge rst);

        while (current_inputs != n_inputs)
        begin
            if (current_inputs <= 20)
            begin
                d_serial_valid = 1'b1;
                d_serial_data  = ~ serial_data;
            end
            else
            begin
                d_serial_valid = 1' ($urandom());
                d_serial_data  = 1' ($urandom());
            end

            current_inputs += 32' (d_serial_valid);

            { serial_valid, serial_data } <= { d_serial_valid, d_serial_data };

            @ (posedge clk);
        end

        // Stop driving and wait for output
        // We have to wait 2 cycles here: one to get an output from the module
        // and another one to wait for non-blocking assignment to out_vld_cnt
        serial_valid <= '0;
        @(posedge clk);
        @(posedge clk);

        if (in_cnt_w' (out_vld_cnt * width) !== in_vld_cnt) begin
            $display ("FAIL %s", `__FILE__);

            $display("++ TEST     => {%s != %s}", `PD(out_vld_cnt*width), `PD(in_vld_cnt));
            $display("++ EXPECTED => out_vld_cnt * width == in_vld_cnt");

            $finish (1);
        end

        $display ("PASS %s", `__FILE__);
        $finish;
    end

endmodule

02_sequential_basics/dump.vcd
$date
	Tue May 27 12:52:34 2025
$end
$version
	Icarus Verilog
$end
$timescale
	1s
$end
$scope module testbench $end
$var wire 1 ! parallel_valid $end
$var wire 8 " parallel_data [7:0] $end
$var parameter 32 # in_cnt_w $end
$var parameter 64 $ n_inputs $end
$var parameter 32 % n_outputs $end
$var parameter 32 & out_cnt_w $end
$var parameter 32 ' width $end
$var reg 1 ( clk $end
$var reg 1 ) d_serial_data $end
$var reg 1 * d_serial_valid $end
$var reg 10 + in_vld_cnt [9:0] $end
$var reg 7 , out_vld_cnt [6:0] $end
$var reg 8 - parallel_data_expected [7:0] $end
$var reg 1 . rst $end
$var reg 1 / serial_data $end
$var reg 1 0 serial_valid $end
$var integer 32 1 current_inputs [31:0] $end
$var reg 1 2 was_reset $end
$scope module dut $end
$var wire 1 ( clk $end
$var wire 1 . rst $end
$var wire 1 / serial_data $end
$var wire 1 0 serial_valid $end
$var parameter 32 3 width $end
$var reg 3 4 count [2:0] $end
$var reg 8 5 mem [7:0] $end
$var reg 8 6 parallel_data [7:0] $end
$var reg 1 ! parallel_valid $end
$upscope $end
$scope begin $ivl_for_loop0 $end
$var integer 32 7 i [31:0] $end
$upscope $end
$upscope $end
$enddefinitions $end
$comment Show the parameter values. $end
$dumpall
b1000 3
b1000 '
b111 &
b1100100 %
b1100100000 $
b1010 #
$end
#0
$dumpvars
b0 7
bx 6
b0 5
b0 4
02
b0 1
00
0/
x.
bx -
bx ,
bx +
x*
x)
0(
bx "
x!
$end
#500
1(
#1000
0(
#1500
1.
1(
#2000
0(
#2500
b0 +
b0 ,
12
1(
#3000
0(
#3500
b1 5
10
1/
b1 1
1)
1*
0.
1(
#4000
0(
#4500
b1 4
b1 +
0/
b10 1
0)
1(
#5000
0(
#5500
b101 5
1/
b10 +
b10 4
b11 1
1)
1(
#6000
0(
#6500
b11 4
b11 +
0/
b100 1
0)
1(
#7000
0(
#7500
b10101 5
1/
b100 +
b100 4
b101 1
1)
1(
#8000
0(
#8500
b101 4
b101 +
0/
b110 1
0)
1(
#9000
0(
#9500
b1010101 5
1/
b110 +
b110 4
b111 1
1)
1(
#10000
0(
#10500
b1010101 "
b1010101 6
1!
b111 4
b111 +
0/
b1000 1
0)
1(
#11000
0(
#11500
1/
b1 ,
b1000 +
b1 5
b0 4
b0 "
b0 6
0!
b1000 7
b1010101 -
b1001 1
1)
1(
#12000
0(
#12500
b1 4
0/
b1001 +
b1010 1
0)
1(
#13000
0(
#13500
b101 5
b1010 +
1/
b10 4
b1011 1
1)
1(
#14000
0(
#14500
b11 4
0/
b1011 +
b1100 1
0)
1(
#15000
0(
#15500
b10101 5
b1100 +
1/
b100 4
b1101 1
1)
1(
#16000
0(
#16500
b101 4
0/
b1101 +
b1110 1
0)
1(
#17000
0(
#17500
b1010101 5
b1110 +
1/
b110 4
b1111 1
1)
1(
#18000
0(
#18500
b1010101 "
b1010101 6
1!
b111 4
0/
b1111 +
b10000 1
0)
1(
#19000
0(
#19500
b10 ,
b10000 +
1/
b1 5
b0 4
b0 "
b0 6
0!
b1000 7
b10001 1
1)
1(
#20000
0(
#20500
b1 4
0/
b10001 +
b10010 1
0)
1(
#21000
0(
#21500
b101 5
b10010 +
1/
b10 4
b10011 1
1)
1(
#22000
0(
#22500
b11 4
0/
b10011 +
b10100 1
0)
1(
#23000
0(
#23500
b10101 5
b10100 +
1/
b100 4
b10101 1
1)
1(
#24000
0(
#24500
b101 4
00
b10101 +
0*
1(
#25000
0(
#25500
b110101 5
10
b10110 1
1*
1(
#26000
0(
#26500
b1110101 5
b110 4
b10110 +
b10111 1
1(
#27000
0(
#27500
b1110101 "
b1110101 6
1!
b10111 +
0/
b111 4
b11000 1
0)
1(
#28000
0(
#28500
b1 5
b0 4
b0 "
b0 6
0!
1/
b11 ,
b11000 +
b1110101 -
b1000 7
b11001 1
1)
1(
#29000
0(
#29500
00
b1 4
b11001 +
0*
1(
#30000
0(
#30500
10
0/
b11010 1
0)
1*
1(
#31000
0(
#31500
b10 4
b11010 +
b11011 1
1(
#32000
0(
#32500
b11011 +
b11 4
b11100 1
1(
#33000
0(
#33500
b10001 5
1/
b100 4
b11100 +
b11101 1
1)
1(
#34000
0(
#34500
b11101 +
b101 4
00
0*
1(
#35000
0(
#35500
0/
0)
1(
#36000
0(
#36500
1/
1)
1(
#37000
0(
#37500
1(
#38000
0(
#38500
b110001 5
10
b11110 1
1*
1(
#39000
0(
#39500
0/
b110 4
b11110 +
b11111 1
0)
1(
#40000
0(
#40500
b11111 +
b111 4
00
0*
1(
#41000
0(
#41500
1/
1)
1(
#42000
0(
#42500
1(
#43000
0(
#43500
b10110001 "
b10110001 6
1!
b10110001 5
10
b100000 1
1*
1(
#44000
0(
#44500
b100 ,
b100000 +
b1 5
b0 4
b0 "
b0 6
0!
b10110001 -
b1000 7
b100001 1
1(
#45000
0(
#45500
00
0/
b1 4
b100001 +
0)
0*
1(
#46000
0(
#46500
b11 5
10
1/
b100010 1
1)
1*
1(
#47000
0(
#47500
0/
b10 4
b100010 +
b100011 1
0)
1(
#48000
0(
#48500
b100011 +
b11 4
00
0*
1(
#49000
0(
#49500
1(
#50000
0(
#50500
10
b100100 1
1*
1(
#51000
0(
#51500
00
1/
b100 4
b100100 +
1)
0*
1(
#52000
0(
#52500
10
0/
b100101 1
0)
1*
1(
#53000
0(
#53500
00
b101 4
b100101 +
0*
1(
#54000
0(
#54500
1(
#55000
0(
#55500
b100011 5
10
1/
b100110 1
1)
1*
1(
#56000
0(
#56500
b1100011 5
b100110 +
b110 4
b100111 1
1(
#57000
0(
#57500
b1100011 "
b1100011 6
1!
0/
b111 4
b100111 +
b101000 1
0)
1(
#58000
0(
#58500
b101 ,
b101000 +
b0 5
b0 4
b0 "
b0 6
0!
00
1/
b1100011 -
b1000 7
1)
0*
1(
#59000
0(
#59500
b1 5
10
b101001 1
1*
1(
#60000
0(
#60500
b101001 +
b1 4
00
0/
0)
0*
1(
#61000
0(
#61500
b11 5
10
1/
b101010 1
1)
1*
1(
#62000
0(
#62500
b101010 +
b10 4
00
0*
1(
#63000
0(
#63500
10
0/
b101011 1
0)
1*
1(
#64000
0(
#64500
b1011 5
b101011 +
b11 4
1/
b101100 1
1)
1(
#65000
0(
#65500
0/
b100 4
b101100 +
b101101 1
0)
1(
#66000
0(
#66500
b101011 5
b101101 +
b101 4
1/
b101110 1
1)
1(
#67000
0(
#67500
00
0/
b110 4
b101110 +
0)
0*
1(
#68000
0(
#68500
1(
#69000
0(
#69500
b1101011 5
10
1/
b101111 1
1)
1*
1(
#70000
0(
#70500
b101111 +
b111 4
00
0/
0)
0*
1(
#71000
0(
#71500
b11101011 "
b11101011 6
1!
b11101011 5
10
1/
b110000 1
1)
1*
1(
#72000
0(
#72500
b110 ,
b110000 +
b1 5
b0 4
b0 "
b0 6
0!
b11101011 -
b1000 7
b110001 1
1(
#73000
0(
#73500
0/
b1 4
b110001 +
b110010 1
0)
1(
#74000
0(
#74500
b101 5
b110010 +
b10 4
1/
b110011 1
1)
1(
#75000
0(
#75500
0/
b11 4
b110011 +
b110100 1
0)
1(
#76000
0(
#76500
b110100 +
b100 4
00
0*
1(
#77000
0(
#77500
1(
#78000
0(
#78500
1(
#79000
0(
#79500
b10101 5
10
1/
b110101 1
1)
1*
1(
#80000
0(
#80500
b110101 5
b110101 +
b101 4
b110110 1
1(
#81000
0(
#81500
0/
b110 4
b110110 +
b110111 1
0)
1(
#82000
0(
#82500
b10110101 "
b10110101 6
1!
b10110101 5
b110111 +
b111 4
1/
b111000 1
1)
1(
#83000
0(
#83500
00
0/
b0 5
b0 4
b0 "
b0 6
0!
b111 ,
b111000 +
b10110101 -
b1000 7
0)
0*
1(
#84000
0(
#84500
b1 5
10
1/
b111001 1
1)
1*
1(
#85000
0(
#85500
b111001 +
00
b1 4
0*
1(
#86000
0(
#86500
b11 5
10
b111010 1
1*
1(
#87000
0(
#87500
b111010 +
0/
b10 4
b111011 1
0)
1(
#88000
0(
#88500
b11 4
00
b111011 +
0*
1(
#89000
0(
#89500
10
b111100 1
1*
1(
#90000
0(
#90500
b100 4
00
b111100 +
0*
1(
#91000
0(
#91500
b10011 5
10
1/
b111101 1
1)
1*
1(
#92000
0(
#92500
b101 4
00
0/
b111101 +
0)
0*
1(
#93000
0(
#93500
10
b111110 1
1*
1(
#94000
0(
#94500
b110 4
00
b111110 +
0*
1(
#95000
0(
#95500
10
b111111 1
1*
1(
#96000
0(
#96500
b111 4
00
1/
b111111 +
1)
0*
1(
#97000
0(
#97500
1(
#98000
0(
#98500
b10010011 "
b10010011 6
1!
b10010011 5
10
b1000000 1
1*
1(
#99000
0(
#99500
b1000 ,
b1000000 +
b1 5
b0 4
b0 "
b0 6
0!
b10010011 -
b1000 7
b1000001 1
1(
#100000
0(
#100500
b1 4
00
0/
b1000001 +
0)
0*
1(
#101000
0(
#101500
1/
1)
1(
#102000
0(
#102500
0/
0)
1(
#103000
0(
#103500
b11 5
10
1/
b1000010 1
1)
1*
1(
#104000
0(
#104500
b10 4
00
0/
b1000010 +
0)
0*
1(
#105000
0(
#105500
1/
1)
1(
#106000
0(
#106500
10
0/
b1000011 1
0)
1*
1(
#107000
0(
#107500
b1000011 +
00
b11 4
0*
1(
#108000
0(
#108500
b1011 5
10
1/
b1000100 1
1)
1*
1(
#109000
0(
#109500
b1000100 +
00
0/
b100 4
0)
0*
1(
#110000
0(
#110500
1/
1)
1(
#111000
0(
#111500
0/
0)
1(
#112000
0(
#112500
10
b1000101 1
1*
1(
#113000
0(
#113500
b1000101 +
00
b101 4
0*
1(
#114000
0(
#114500
10
b1000110 1
1*
1(
#115000
0(
#115500
b1001011 5
b1000110 +
1/
b110 4
b1000111 1
1)
1(
#116000
0(
#116500
b111 4
00
0/
b1000111 +
0)
0*
1(
#117000
0(
#117500
1(
#118000
0(
#118500
b1001011 "
b1001011 6
1!
10
b1001000 1
1*
1(
#119000
0(
#119500
b1001 ,
b1001000 +
00
b0 5
b0 4
b0 "
b0 6
0!
b1001011 -
b1000 7
0*
1(
#120000
0(
#120500
1/
1)
1(
#121000
0(
#121500
b1 5
10
b1001001 1
1*
1(
#122000
0(
#122500
b1 4
00
b1001001 +
0*
1(
#123000
0(
#123500
b11 5
10
b1001010 1
1*
1(
#124000
0(
#124500
b10 4
00
0/
b1001010 +
0)
0*
1(
#125000
0(
#125500
b111 5
10
1/
b1001011 1
1)
1*
1(
#126000
0(
#126500
b1111 5
b11 4
b1001011 +
b1001100 1
1(
#127000
0(
#127500
b1001100 +
0/
b100 4
b1001101 1
0)
1(
#128000
0(
#128500
b101111 5
b101 4
1/
b1001101 +
b1001110 1
1)
1(
#129000
0(
#129500
b1001110 +
00
0/
b110 4
0)
0*
1(
#130000
0(
#130500
1(
#131000
0(
#131500
b1101111 5
10
1/
b1001111 1
1)
1*
1(
#132000
0(
#132500
b111 4
00
0/
b1001111 +
0)
0*
1(
#133000
0(
#133500
b1101111 "
b1101111 6
1!
10
b1010000 1
1*
1(
#134000
0(
#134500
b0 5
b0 4
b0 "
b0 6
0!
00
1/
b1010 ,
b1010000 +
b1101111 -
b1000 7
1)
0*
1(
#135000
0(
#135500
0/
0)
1(
#136000
0(
#136500
10
b1010001 1
1*
1(
#137000
0(
#137500
00
1/
b1 4
b1010001 +
1)
0*
1(
#138000
0(
#138500
b10 5
10
b1010010 1
1*
1(
#139000
0(
#139500
00
0/
b10 4
b1010010 +
0)
0*
1(
#140000
0(
#140500
1/
1)
1(
#141000
0(
#141500
0/
0)
1(
#142000
0(
#142500
10
b1010011 1
1*
1(
#143000
0(
#143500
00
b11 4
b1010011 +
0*
1(
#144000
0(
#144500
1/
1)
1(
#145000
0(
#145500
0/
0)
1(
#146000
0(
#146500
1/
1)
1(
#147000
0(
#147500
10
0/
b1010100 1
0)
1*
1(
#148000
0(
#148500
b10010 5
b1010100 +
b100 4
1/
b1010101 1
1)
1(
#149000
0(
#149500
b110010 5
b101 4
b1010101 +
b1010110 1
1(
#150000
0(
#150500
b1010110 +
b110 4
00
0*
1(
#151000
0(
#151500
b1110010 5
10
b1010111 1
1*
1(
#152000
0(
#152500
b1010111 +
b111 4
00
0/
0)
0*
1(
#153000
0(
#153500
b1110010 "
b1110010 6
1!
10
b1011000 1
1*
1(
#154000
0(
#154500
b1011 ,
b1011000 +
b0 5
b0 4
b0 "
b0 6
0!
00
1/
b1110010 -
b1000 7
1)
0*
1(
#155000
0(
#155500
10
0/
b1011001 1
0)
1*
1(
#156000
0(
#156500
b1011001 +
b1 4
00
1/
1)
0*
1(
#157000
0(
#157500
0/
0)
1(
#158000
0(
#158500
10
b1011010 1
1*
1(
#159000
0(
#159500
b100 5
1/
b10 4
b1011010 +
b1011011 1
1)
1(
#160000
0(
#160500
b1011011 +
b11 4
00
0*
1(
#161000
0(
#161500
1(
#162000
0(
#162500
0/
0)
1(
#163000
0(
#163500
10
b1011100 1
1*
1(
#164000
0(
#164500
b1011100 +
b100 4
00
0*
1(
#165000
0(
#165500
b10100 5
10
1/
b1011101 1
1)
1*
1(
#166000
0(
#166500
b110100 5
b1011101 +
b101 4
b1011110 1
1(
#167000
0(
#167500
0/
b110 4
b1011110 +
b1011111 1
0)
1(
#168000
0(
#168500
b10110100 "
b10110100 6
1!
b10110100 5
b1011111 +
b111 4
1/
b1100000 1
1)
1(
#169000
0(
#169500
0/
b0 5
b0 4
b0 "
b0 6
0!
b1100 ,
b1100000 +
b10110100 -
b1000 7
b1100001 1
0)
1(
#170000
0(
#170500
b1 4
00
b1100001 +
0*
1(
#171000
0(
#171500
1(
#172000
0(
#172500
1/
1)
1(
#173000
0(
#173500
b10 5
10
b1100010 1
1*
1(
#174000
0(
#174500
b110 5
b10 4
b1100010 +
b1100011 1
1(
#175000
0(
#175500
b1110 5
b1100011 +
b11 4
b1100100 1
1(
#176000
0(
#176500
b100 4
00
b1100100 +
0*
1(
#177000
0(
#177500
b11110 5
10
b1100101 1
1*
1(
#178000
0(
#178500
b111110 5
b101 4
b1100101 +
b1100110 1
1(
#179000
0(
#179500
b1111110 5
b1100110 +
b110 4
b1100111 1
1(
#180000
0(
#180500
b1111110 "
b1111110 6
1!
b111 4
0/
b1100111 +
b1101000 1
0)
1(
#181000
0(
#181500
b1101 ,
b1101000 +
00
1/
b0 5
b0 4
b0 "
b0 6
0!
b1111110 -
b1000 7
1)
0*
1(
#182000
0(
#182500
10
0/
b1101001 1
0)
1*
1(
#183000
0(
#183500
b1101001 +
00
b1 4
0*
1(
#184000
0(
#184500
1/
1)
1(
#185000
0(
#185500
0/
0)
1(
#186000
0(
#186500
1(
#187000
0(
#187500
1(
#188000
0(
#188500
10
b1101010 1
1*
1(
#189000
0(
#189500
b1101010 +
00
1/
b10 4
1)
0*
1(
#190000
0(
#190500
0/
0)
1(
#191000
0(
#191500
1(
#192000
0(
#192500
b100 5
10
1/
b1101011 1
1)
1*
1(
#193000
0(
#193500
b1100 5
b1101011 +
b11 4
b1101100 1
1(
#194000
0(
#194500
b100 4
0/
b1101100 +
b1101101 1
0)
1(
#195000
0(
#195500
b101100 5
b1101101 +
1/
b101 4
b1101110 1
1)
1(
#196000
0(
#196500
b110 4
0/
b1101110 +
b1101111 1
0)
1(
#197000
0(
#197500
b101100 "
b101100 6
1!
b1101111 +
b111 4
b1110000 1
1(
#198000
0(
#198500
b0 5
b0 4
b0 "
b0 6
0!
00
1/
b1110 ,
b1110000 +
b101100 -
b1000 7
1)
0*
1(
#199000
0(
#199500
10
0/
b1110001 1
0)
1*
1(
#200000
0(
#200500
b1110001 +
b1 4
b1110010 1
1(
#201000
0(
#201500
00
1/
b10 4
b1110010 +
1)
0*
1(
#202000
0(
#202500
0/
0)
1(
#203000
0(
#203500
1(
#204000
0(
#204500
b100 5
10
1/
b1110011 1
1)
1*
1(
#205000
0(
#205500
b1100 5
b11 4
b1110011 +
b1110100 1
1(
#206000
0(
#206500
b1110100 +
b100 4
00
0*
1(
#207000
0(
#207500
b11100 5
10
b1110101 1
1*
1(
#208000
0(
#208500
b111100 5
b1110101 +
b101 4
b1110110 1
1(
#209000
0(
#209500
b1111100 5
b110 4
b1110110 +
b1110111 1
1(
#210000
0(
#210500
b1110111 +
b111 4
00
0*
1(
#211000
0(
#211500
1(
#212000
0(
#212500
0/
0)
1(
#213000
0(
#213500
b1111100 "
b1111100 6
1!
10
b1111000 1
1*
1(
#214000
0(
#214500
b1111 ,
b1111000 +
b0 5
b0 4
b0 "
b0 6
0!
00
b1111100 -
b1000 7
0*
1(
#215000
0(
#215500
1(
#216000
0(
#216500
10
b1111001 1
1*
1(
#217000
0(
#217500
00
b1 4
b1111001 +
0*
1(
#218000
0(
#218500
1(
#219000
0(
#219500
1/
1)
1(
#220000
0(
#220500
1(
#221000
0(
#221500
0/
0)
1(
#222000
0(
#222500
10
b1111010 1
1*
1(
#223000
0(
#223500
b100 5
1/
b10 4
b1111010 +
b1111011 1
1)
1(
#224000
0(
#224500
b1111011 +
b11 4
00
0*
1(
#225000
0(
#225500
1(
#226000
0(
#226500
0/
0)
1(
#227000
0(
#227500
1(
#228000
0(
#228500
10
b1111100 1
1*
1(
#229000
0(
#229500
b100 4
b1111100 +
b1111101 1
1(
#230000
0(
#230500
b100100 5
b1111101 +
b101 4
1/
b1111110 1
1)
1(
#231000
0(
#231500
00
b110 4
b1111110 +
0*
1(
#232000
0(
#232500
1(
#233000
0(
#233500
b1100100 5
10
b1111111 1
1*
1(
#234000
0(
#234500
b1111111 +
b111 4
00
0*
1(
#235000
0(
#235500
b1100100 "
b1100100 6
1!
10
0/
b10000000 1
0)
1*
1(
#236000
0(
#236500
b10000 ,
b10000000 +
b0 5
b0 4
b0 "
b0 6
0!
00
1/
b1100100 -
b1000 7
1)
0*
1(
#237000
0(
#237500
10
0/
b10000001 1
0)
1*
1(
#238000
0(
#238500
b10000001 +
b1 4
00
1/
1)
0*
1(
#239000
0(
#239500
10
0/
b10000010 1
0)
1*
1(
#240000
0(
#240500
b10000010 +
b10 4
00
1/
1)
0*
1(
#241000
0(
#241500
0/
0)
1(
#242000
0(
#242500
b100 5
10
1/
b10000011 1
1)
1*
1(
#243000
0(
#243500
00
0/
b11 4
b10000011 +
0)
0*
1(
#244000
0(
#244500
10
b10000100 1
1*
1(
#245000
0(
#245500
00
1/
b100 4
b10000100 +
1)
0*
1(
#246000
0(
#246500
10
0/
b10000101 1
0)
1*
1(
#247000
0(
#247500
b101 4
b10000101 +
b10000110 1
1(
#248000
0(
#248500
b1000100 5
b10000110 +
b110 4
1/
b10000111 1
1)
1(
#249000
0(
#249500
00
b111 4
b10000111 +
0*
1(
#250000
0(
#250500
b11000100 "
b11000100 6
1!
b11000100 5
10
b10001000 1
1*
1(
#251000
0(
#251500
00
b0 5
b0 4
b0 "
b0 6
0!
b10001 ,
b10001000 +
b11000100 -
b1000 7
0*
1(
#252000
0(
#252500
b1 5
10
b10001001 1
1*
1(
#253000
0(
#253500
b10001001 +
00
0/
b1 4
0)
0*
1(
#254000
0(
#254500
10
b10001010 1
1*
1(
#255000
0(
#255500
b10001010 +
00
1/
b10 4
1)
0*
1(
#256000
0(
#256500
0/
0)
1(
#257000
0(
#257500
b101 5
10
1/
b10001011 1
1)
1*
1(
#258000
0(
#258500
b11 4
00
b10001011 +
0*
1(
#259000
0(
#259500
1(
#260000
0(
#260500
b1101 5
10
b10001100 1
1*
1(
#261000
0(
#261500
b10001100 +
0/
b100 4
b10001101 1
0)
1(
#262000
0(
#262500
b101 4
00
1/
b10001101 +
1)
0*
1(
#263000
0(
#263500
1(
#264000
0(
#264500
1(
#265000
0(
#265500
10
0/
b10001110 1
0)
1*
1(
#266000
0(
#266500
b110 4
00
1/
b10001110 +
1)
0*
1(
#267000
0(
#267500
b1001101 5
10
b10001111 1
1*
1(
#268000
0(
#268500
b111 4
00
0/
b10001111 +
0)
0*
1(
#269000
0(
#269500
b1001101 "
b1001101 6
1!
10
b10010000 1
1*
1(
#270000
0(
#270500
b0 5
b0 4
b0 "
b0 6
0!
00
1/
b10010 ,
b10010000 +
b1001101 -
b1000 7
1)
0*
1(
#271000
0(
#271500
b1 5
10
b10010001 1
1*
1(
#272000
0(
#272500
b10010001 +
b1 4
00
0*
1(
#273000
0(
#273500
10
0/
b10010010 1
0)
1*
1(
#274000
0(
#274500
b10010010 +
b10 4
00
0*
1(
#275000
0(
#275500
b101 5
10
1/
b10010011 1
1)
1*
1(
#276000
0(
#276500
b10010011 +
b11 4
0/
b10010100 1
0)
1(
#277000
0(
#277500
00
b100 4
b10010100 +
0*
1(
#278000
0(
#278500
b10101 5
10
1/
b10010101 1
1)
1*
1(
#279000
0(
#279500
b110101 5
b101 4
b10010101 +
b10010110 1
1(
#280000
0(
#280500
b10010110 +
b110 4
00
0*
1(
#281000
0(
#281500
b1110101 5
10
b10010111 1
1*
1(
#282000
0(
#282500
b11110101 "
b11110101 6
1!
b11110101 5
b10010111 +
b111 4
b10011000 1
1(
#283000
0(
#283500
b1 5
b0 4
b0 "
b0 6
0!
b10011 ,
b10011000 +
b11110101 -
b1000 7
b10011001 1
1(
#284000
0(
#284500
b1 4
00
b10011001 +
0*
1(
#285000
0(
#285500
0/
0)
1(
#286000
0(
#286500
1/
1)
1(
#287000
0(
#287500
b11 5
10
b10011010 1
1*
1(
#288000
0(
#288500
b111 5
b10 4
b10011010 +
b10011011 1
1(
#289000
0(
#289500
b1111 5
b10011011 +
b11 4
b10011100 1
1(
#290000
0(
#290500
b11111 5
b100 4
b10011100 +
b10011101 1
1(
#291000
0(
#291500
b10011101 +
00
0/
b101 4
0)
0*
1(
#292000
0(
#292500
1/
1)
1(
#293000
0(
#293500
0/
0)
1(
#294000
0(
#294500
1/
1)
1(
#295000
0(
#295500
10
0/
b10011110 1
0)
1*
1(
#296000
0(
#296500
b110 4
00
b10011110 +
0*
1(
#297000
0(
#297500
b1011111 5
10
1/
b10011111 1
1)
1*
1(
#298000
0(
#298500
b111 4
00
b10011111 +
0*
1(
#299000
0(
#299500
1(
#300000
0(
#300500
0/
0)
1(
#301000
0(
#301500
1/
1)
1(
#302000
0(
#302500
b11011111 "
b11011111 6
1!
b11011111 5
10
b10100000 1
1*
1(
#303000
0(
#303500
b10100 ,
b10100000 +
00
b0 5
b0 4
b0 "
b0 6
0!
b11011111 -
b1000 7
0*
1(
#304000
0(
#304500
1(
#305000
0(
#305500
1(
#306000
0(
#306500
10
0/
b10100001 1
0)
1*
1(
#307000
0(
#307500
b10100001 +
00
b1 4
0*
1(
#308000
0(
#308500
1/
1)
1(
#309000
0(
#309500
10
0/
b10100010 1
0)
1*
1(
#310000
0(
#310500
b10 4
00
1/
b10100010 +
1)
0*
1(
#311000
0(
#311500
1(
#312000
0(
#312500
1(
#313000
0(
#313500
10
0/
b10100011 1
0)
1*
1(
#314000
0(
#314500
b1000 5
b11 4
1/
b10100011 +
b10100100 1
1)
1(
#315000
0(
#315500
b10100100 +
00
0/
b100 4
0)
0*
1(
#316000
0(
#316500
1(
#317000
0(
#317500
b11000 5
10
1/
b10100101 1
1)
1*
1(
#318000
0(
#318500
b111000 5
b101 4
b10100101 +
b10100110 1
1(
#319000
0(
#319500
b10100110 +
0/
b110 4
b10100111 1
0)
1(
#320000
0(
#320500
b111 4
00
b10100111 +
0*
1(
#321000
0(
#321500
1(
#322000
0(
#322500
1(
#323000
0(
#323500
b10111000 "
b10111000 6
1!
b10111000 5
10
1/
b10101000 1
1)
1*
1(
#324000
0(
#324500
b1 5
b0 4
b0 "
b0 6
0!
b10101 ,
b10101000 +
b10111000 -
b1000 7
b10101001 1
1(
#325000
0(
#325500
b11 5
b1 4
b10101001 +
b10101010 1
1(
#326000
0(
#326500
b10101010 +
b10 4
0/
b10101011 1
0)
1(
#327000
0(
#327500
00
b11 4
b10101011 +
0*
1(
#328000
0(
#328500
1(
#329000
0(
#329500
1/
1)
1(
#330000
0(
#330500
10
0/
b10101100 1
0)
1*
1(
#331000
0(
#331500
b100 4
b10101100 +
b10101101 1
1(
#332000
0(
#332500
b100011 5
b10101101 +
b101 4
1/
b10101110 1
1)
1(
#333000
0(
#333500
0/
b110 4
b10101110 +
b10101111 1
0)
1(
#334000
0(
#334500
b10101111 +
b111 4
00
0*
1(
#335000
0(
#335500
b10100011 "
b10100011 6
1!
b10100011 5
10
1/
b10110000 1
1)
1*
1(
#336000
0(
#336500
b10110 ,
b10110000 +
b0 5
b0 4
b0 "
b0 6
0!
00
b10100011 -
b1000 7
0*
1(
#337000
0(
#337500
0/
0)
1(
#338000
0(
#338500
1(
#339000
0(
#339500
1(
#340000
0(
#340500
10
b10110001 1
1*
1(
#341000
0(
#341500
00
1/
b1 4
b10110001 +
1)
0*
1(
#342000
0(
#342500
0/
0)
1(
#343000
0(
#343500
b10 5
10
1/
b10110010 1
1)
1*
1(
#344000
0(
#344500
b10110010 +
b10 4
0/
b10110011 1
0)
1(
#345000
0(
#345500
00
1/
b11 4
b10110011 +
1)
0*
1(
#346000
0(
#346500
b1010 5
10
b10110100 1
1*
1(
#347000
0(
#347500
0/
b100 4
b10110100 +
b10110101 1
0)
1(
#348000
0(
#348500
b101010 5
b10110101 +
b101 4
1/
b10110110 1
1)
1(
#349000
0(
#349500
b1101010 5
b110 4
b10110110 +
b10110111 1
1(
#350000
0(
#350500
b10110111 +
b111 4
00
0*
1(
#351000
0(
#351500
0/
0)
1(
#352000
0(
#352500
b1101010 "
b1101010 6
1!
10
b10111000 1
1*
1(
#353000
0(
#353500
00
1/
b0 5
b0 4
b0 "
b0 6
0!
b10111 ,
b10111000 +
b1101010 -
b1000 7
1)
0*
1(
#354000
0(
